pyfilterfile.cpython-313-darwin.so
foton.py
pydmtsigp.cpython-313-darwin.so
python_foton.dylibs/libc++.1.0.dylib
python_foton.dylibs/libfilterfile.0.0.1.so
python_foton.dylibs/libfftw3f.3.dylib
python_foton.dylibs/libz.1.3.1.dylib
python_foton.dylibs/libgdsmath.2.dylib
python_foton.dylibs/libexpat.1.10.2.dylib
python_foton.dylibs/libgdscntr.10.dylib
python_foton.dylibs/libdmtsigp.1.dylib
python_foton.dylibs/libfftw3.3.dylib
python_foton.dylibs/libgdsbase.9.dylib
python_foton-4.1.5.dist-info/RECORD
python_foton-4.1.5.dist-info/WHEEL
python_foton-4.1.5.dist-info/top_level.txt
python_foton-4.1.5.dist-info/METADATA
python_foton-4.1.5.dist-info/licenses/COPYING-GPL-3
python_foton-4.1.5.dist-info/licenses/COPYING
