Metadata-Version: 2.4
Name: python-foton
Version: 4.1.5
Home-page: https://git.ligo.org/cds/software/dtt
Requires-Python: >=3.9
License-File: COPYING
License-File: COPYING-GPL-3
Requires-Dist: numpy
Requires-Dist: scipy
Dynamic: home-page
Dynamic: license-file
Dynamic: requires-dist
Dynamic: requires-python
